Levenshtein_search.pyd
Levenshtein_search-1.4.6.dist-info/LICENSE
Levenshtein_search-1.4.6.dist-info/METADATA
Levenshtein_search-1.4.6.dist-info/WHEEL
Levenshtein_search-1.4.6.dist-info/top_level.txt
Levenshtein_search-1.4.6.dist-info/RECORD
