Metadata-Version: 2.1
Name: Levenshtein-search
Version: 1.4.6
Summary: Search through documents for approximately matching strings
Home-page: https://github.com/mattandahalfew/Levenshtein_search
Author: Matt Anderson
Author-email: manderson3606@gmail.com
License: UNKNOWN
Platform: UNKNOWN
Classifier: Topic :: Software Development :: Libraries :: Python Modules
Classifier: Topic :: Scientific/Engineering
Classifier: Topic :: Scientific/Engineering :: Information Analysis
Classifier: License :: OSI Approved :: GNU General Public License v3 (GPLv3)
